llama_index_instrumentation/__init__.py
llama_index_instrumentation/dispatcher.py
llama_index_instrumentation/py.typed
llama_index_instrumentation/base/__init__.py
llama_index_instrumentation/base/event.py
llama_index_instrumentation/base/handler.py
llama_index_instrumentation/event_handlers/__init__.py
llama_index_instrumentation/event_handlers/base.py
llama_index_instrumentation/event_handlers/null.py
llama_index_instrumentation/events/__init__.py
llama_index_instrumentation/events/span.py
llama_index_instrumentation/span/__init__.py
llama_index_instrumentation/span/base.py
llama_index_instrumentation/span/simple.py
llama_index_instrumentation/span_handlers/__init__.py
llama_index_instrumentation/span_handlers/base.py
llama_index_instrumentation/span_handlers/null.py
llama_index_instrumentation/span_handlers/simple.py
llama_index_instrumentation-0.3.1.dist-info/METADATA
llama_index_instrumentation-0.3.1.dist-info/WHEEL
llama_index_instrumentation-0.3.1.dist-info/entry_points.txt
llama_index_instrumentation-0.3.1.dist-info/RECORD
