Metadata-Version: 2.4
Name: llama-index-instrumentation
Version: 0.3.1
Summary: Add your description here
Author-email: Massimiliano Pippi <mpippi@gmail.com>
Requires-Python: <4.0,>=3.9
Requires-Dist: deprecated>=1.2.18
Requires-Dist: pydantic>=2.11.5
